mat3ra/__init__.py
mat3ra/api_client/__init__.py
mat3ra/api_client/_version.py
mat3ra/api_client/client.py
mat3ra/api_client/endpoints/__init__.py
mat3ra/api_client/endpoints/bank_entity.py
mat3ra/api_client/endpoints/bank_materials.py
mat3ra/api_client/endpoints/bank_workflows.py
mat3ra/api_client/endpoints/charges.py
mat3ra/api_client/endpoints/entity.py
mat3ra/api_client/endpoints/enums.py
mat3ra/api_client/endpoints/jobs.py
mat3ra/api_client/endpoints/login.py
mat3ra/api_client/endpoints/logout.py
mat3ra/api_client/endpoints/materials.py
mat3ra/api_client/endpoints/metaproperties.py
mat3ra/api_client/endpoints/projects.py
mat3ra/api_client/endpoints/properties.py
mat3ra/api_client/endpoints/workflows.py
mat3ra/api_client/endpoints/mixins/__init__.py
mat3ra/api_client/endpoints/mixins/default.py
mat3ra/api_client/endpoints/mixins/set.py
mat3ra/api_client/utils/__init__.py
mat3ra/api_client/utils/http.py
mat3ra/api_client/utils/materials.py
mat3ra_api_client-2025.12.26.post0.dist-info/licenses/LICENSE.md
mat3ra_api_client-2025.12.26.post0.dist-info/METADATA
mat3ra_api_client-2025.12.26.post0.dist-info/WHEEL
mat3ra_api_client-2025.12.26.post0.dist-info/top_level.txt
mat3ra_api_client-2025.12.26.post0.dist-info/RECORD
